LICENSE
README.md
setup.py
mywebdriver.egg-info/PKG-INFO
mywebdriver.egg-info/SOURCES.txt
mywebdriver.egg-info/dependency_links.txt
mywebdriver.egg-info/requires.txt
mywebdriver.egg-info/top_level.txt
mywebdriver/chrome/__init__.py
mywebdriver/chrome/chromedriver.py