Metadata-Version: 2.1
Name: mywebdriver
Version: 1.2.0
Summary: A quick library to install your webdriver according to your browser version
Home-page: https://github.com/gabriellopesdesouza2002/mywebdriver
Author: Gabriel Lopes de Souza
Author-email: gabriellopesdesouza2002@gmail.com
License: MIT License
Keywords: A quick library to install your webdriver according to your browser version
License-File: LICENSE
